longer_limbs/__init__.py
longer_limbs/regressors.py
longer_limbs-1.0a1.dist-info/METADATA
longer_limbs-1.0a1.dist-info/WHEEL
longer_limbs-1.0a1.dist-info/licenses/LICENSE
longer_limbs-1.0a1.dist-info/RECORD
